{
	"jeebs": {
		"app": {
			"name": "Razor",
			"suite": "Jeebs"
		},
		"db": {
			"default": "test",
			"authentication": "test",
			"connections": {
				"test": {
					"connectionString": ""
				}
			}
		},
		"logging": {
			"minimum": "Verbose",
			"overrides": {
				"Microsoft": "Warning",
				"Microsoft.Hosting.Lifetime": "Information"
			},
			"providers": {
				"console": {
					"enabled": true
				},
				"seq.server04": {
					"enabled": true
				}
			}
		},
		"services": {
			"seq": {
				"server04": {
					"server": "",
					"apiKey": ""
				}
			}
		},
		"web": {
			"auth": {
				"enabled": true,
				"scheme": "jwt"
			}
		}
	}
}